langchain_uagents/__init__.py
langchain_uagents/tools.py
langchain_uagents-0.1.1.dist-info/LICENSE
langchain_uagents-0.1.1.dist-info/METADATA
langchain_uagents-0.1.1.dist-info/WHEEL
langchain_uagents-0.1.1.dist-info/RECORD
