Metadata-Version: 2.3
Name: langchain-uagents
Version: 0.1.1
Summary: Bridge Langchain agents with uAgents and register them on Agentverse
License: MIT
Author: Abhi Gangani
Author-email: abhi.gangani@fetch.ai
Requires-Python: >=3.10,<4.0
Classifier: License :: OSI Approved :: MIT License
Classifier: Programming Language :: Python :: 3
Classifier: Programming Language :: Python :: 3.10
Classifier: Programming Language :: Python :: 3.11
Classifier: Programming Language :: Python :: 3.12
Classifier: Programming Language :: Python :: 3.13
Requires-Dist: langchain (>=0.3.21,<0.4.0)
Requires-Dist: langchain-core (>=0.3.48,<0.4.0)
Requires-Dist: langchain-openai (>=0.2.0,<0.3.0)
Requires-Dist: pydantic (>=2.10.6,<3.0.0)
Requires-Dist: python-dotenv (>=1.0.0,<2.0.0)
Requires-Dist: requests (>=2.32.3,<3.0.0)
Requires-Dist: uagents (>=0.21.0,<0.22.0)
Project-URL: Documentation, https://github.com/fetchai/langchain-uagents#readme
Project-URL: Repository, https://github.com/fetchai/langchain-uagents
